
[
    {

    "wallpaper_index": "45",

    "wallpaper_name": "Frozen 2 HD-4k",

    "wallpaper_site_name": "imgur",

    "wallpaper_site_url": "https://wallpapercave.com",

    "wallpaper_url": "https://wallpapercave.com/wp/wp4413314.jpg"

  },
    {

    "wallpaper_index": "46",

    "wallpaper_name": "Frozen 2 HD-4k",

    "wallpaper_site_name": "imgur",

    "wallpaper_site_url": "https://wallpapercave.com",

    "wallpaper_url": "https://wallpapercave.com/wp/wp4678240.jpg"

  },
    {

    "wallpaper_index": "407",

    "wallpaper_name": "Frozen 2 HD-4k",

    "wallpaper_site_name": "imgur",

    "wallpaper_site_url": "https://wallpapercave.com",

    "wallpaper_url": "https://wallpapercave.com/wp/wp4678241.jpg"

  },
    {

    "wallpaper_index": "48",

    "wallpaper_name": "Frozen 2 HD-4k",

    "wallpaper_site_name": "imgur",

    "wallpaper_site_url": "https://wallpapercave.com",

    "wallpaper_url": "https://wallpapercave.com/wp/wp4678242.jpg"

  },
    {

    "wallpaper_index": "49",

    "wallpaper_name": "Frozen 2 HD-4k",

    "wallpaper_site_name": "imgur",

    "wallpaper_site_url": "https://wallpapercave.com",

    "wallpaper_url": "https://wallpapercave.com/wp/wp4599551.jpg"

  },
    {

    "wallpaper_index": "4100",

    "wallpaper_name": "Frozen 2 HD-4k",

    "wallpaper_site_name": "imgur",

    "wallpaper_site_url": "https://wallpapercave.com",

    "wallpaper_url": "https://wallpapercave.com/wp/wp4531891.jpg"

  },
    {

    "wallpaper_index": "4110",

    "wallpaper_name": "Frozen 2 HD-4k",

    "wallpaper_site_name": "imgur",

    "wallpaper_site_url": "https://wallpapercave.com",

    "wallpaper_url": "https://wallpapercave.com/wp/wp4678245.jpg"

  },
    {

    "wallpaper_index": "4120",

    "wallpaper_name": "Frozen 2 HD-4k",

    "wallpaper_site_name": "imgur",

    "wallpaper_site_url": "https://wallpapercave.com",

    "wallpaper_url": "https://wallpapercave.com/wp/wp1987829.jpg"

  },
    {

    "wallpaper_index": "4130",

    "wallpaper_name": "Frozen 2 HD-4k",

    "wallpaper_site_name": "imgur",

    "wallpaper_site_url": "https://wallpapercave.com",

    "wallpaper_url": "https://wallpapercave.com/wp/wp4531894.jpg"

  },
    {

    "wallpaper_index": "4140",

    "wallpaper_name": "Frozen 2 HD-4k",

    "wallpaper_site_name": "imgur",

    "wallpaper_site_url": "https://wallpapercave.com",

    "wallpaper_url": "https://wallpapercave.com/w/wp1984701"

  },
    {

    "wallpaper_index": "4150",

    "wallpaper_name": "Frozen 2 HD-4k",

    "wallpaper_site_name": "imgur",

    "wallpaper_site_url": "https://wallpapercave.com",

    "wallpaper_url": "https://wallpapercave.com/wp/wp4599576.jpg"

  },
    {

    "wallpaper_index": "4160",

    "wallpaper_name": "Frozen 2 HD-4k",

    "wallpaper_site_name": "imgur",

    "wallpaper_site_url": "https://wallpapercave.com",

    "wallpaper_url": "https://wallpapercave.com/wp/wp4678250.jpg"

  },
    {

    "wallpaper_index": "4107",

    "wallpaper_name": "Frozen 2 HD-4k",

    "wallpaper_site_name": "imgur",

    "wallpaper_site_url": "https://wallpapercave.com",

    "wallpaper_url": "https://wallpapercave.com/wp/wp4531898.jpg"

  },
    {

    "wallpaper_index": "4108",

    "wallpaper_name": "Frozen 2 HD-4k",

    "wallpaper_site_name": "imgur",

    "wallpaper_site_url": "https://wallpapercave.com",

    "wallpaper_url": "https://wallpapercave.com/wp/wp1987896.jpg"

  },
    {

    "wallpaper_index": "4109",

    "wallpaper_name": "Frozen 2 HD-4k",

    "wallpaper_site_name": "imgur",

    "wallpaper_site_url": "https://wallpapercave.com",

    "wallpaper_url": "https://wallpapercave.com/wp/wp4678253.jpg"

  },
    {

    "wallpaper_index": "4200",

    "wallpaper_name": "Frozen 2 HD-4k",

    "wallpaper_site_name": "imgur",

    "wallpaper_site_url": "https://wallpapercave.com",

    "wallpaper_url": "https://wallpapercave.com/wp/wp4599613.jpg"

  },
    {

    "wallpaper_index": "4201",

    "wallpaper_name": "Frozen 2 HD-4k",

    "wallpaper_site_name": "imgur",

    "wallpaper_site_url": "https://wallpapercave.com",

    "wallpaper_url": "https://wallpapercave.com/wp/wp4678257.jpg"

  },
    {

    "wallpaper_index": "4220",

    "wallpaper_name": "Frozen 2 HD-4k",

    "wallpaper_site_name": "imgur",

    "wallpaper_site_url": "https://wallpapercave.com",

    "wallpaper_url": "https://wallpapercave.com/wp/wp4678261.jpg"

  },
    {

    "wallpaper_index": "4203",

    "wallpaper_name": "Frozen 2 HD-4k",

    "wallpaper_site_name": "imgur",

    "wallpaper_site_url": "https://wallpapercave.com",

    "wallpaper_url": "https://wallpapercave.com/wp/wp4678269.jpg"

  },
    {

    "wallpaper_index": "4204",

    "wallpaper_name": "Frozen 2 HD-4k",

    "wallpaper_site_name": "imgur",

    "wallpaper_site_url": "https://wallpapercave.com",

    "wallpaper_url": "https://wallpapercave.com/wp/wp4599574.png"

  },
    {

    "wallpaper_index": "4205",

    "wallpaper_name": "Frozen 2 HD-4k",

    "wallpaper_site_name": "imgur",

    "wallpaper_site_url": "https://wallpapercave.com",

    "wallpaper_url": "https://wallpapercave.com/wp/wp4678271.jpg"

  },
    {

    "wallpaper_index": "4260",

    "wallpaper_name": "Frozen 2 HD-4k",

    "wallpaper_site_name": "imgur",

    "wallpaper_site_url": "https://wallpapercave.com",

    "wallpaper_url": "https://wallpapercave.com/wp/wp4531907.jpg"

  },
    {

    "wallpaper_index": "4270",

    "wallpaper_name": "Frozen 2 HD-4k",

    "wallpaper_site_name": "imgur",

    "wallpaper_site_url": "https://wallpapercave.com",

    "wallpaper_url": "https://wallpapercave.com/wp/wp4413374.jpg"

  },
   {

    "wallpaper_index": "4280",

    "wallpaper_name": "Frozen 2 HD-4k",

    "wallpaper_site_name": "imgur",

    "wallpaper_site_url": "https://wallpapercave.com",

    "wallpaper_url": "https://wallpapercave.com/wp/wp4678277.jpg"

  },
   {

    "wallpaper_index": "4290",

    "wallpaper_name": "Frozen 2 HD-4k",

    "wallpaper_site_name": "imgur",

    "wallpaper_site_url": "https://wallpapercave.com",

    "wallpaper_url": "https://wallpapercave.com/wp/wp4531910.jpg"

  },
   {

    "wallpaper_index": "4300",

    "wallpaper_name": "Frozen 2 HD-4k",

    "wallpaper_site_name": "imgur",

    "wallpaper_site_url": "https://wallpapercave.com",

    "wallpaper_url": "https://wallpapercave.com/wp/wp4678280.jpg"

  },
   {

    "wallpaper_index": "4310",

    "wallpaper_name": "Frozen 2 HD-4k",

    "wallpaper_site_name": "imgur",

    "wallpaper_site_url": "https://wallpapercave.com",

    "wallpaper_url": "https://wallpapercave.com/wp/wp4678283.jpg"

  },
   {

    "wallpaper_index": "4320",

    "wallpaper_name": "Frozen 2 HD-4k",

    "wallpaper_site_name": "imgur",

    "wallpaper_site_url": "https://wallpapercave.com",

    "wallpaper_url": "https://wallpapercave.com/wp/wp4531913.jpg"

  },
   {

    "wallpaper_index": "4330",

    "wallpaper_name": "Frozen 2 HD-4k",

    "wallpaper_site_name": "imgur",

    "wallpaper_site_url": "https://wallpapercave.com",

    "wallpaper_url": "https://wallpapercave.com/wp/wp4678286.jpg"

  },
   {

    "wallpaper_index": "4340",

    "wallpaper_name": "Frozen 2 HD-4k",

    "wallpaper_site_name": "imgur",

    "wallpaper_site_url": "https://wallpapercave.com",

    "wallpaper_url": "https://wallpapercave.com/wp/wp4678293.jpg"

  },
   {

    "wallpaper_index": "4350",

    "wallpaper_name": "Frozen 2 HD-4k",

    "wallpaper_site_name": "imgur",

    "wallpaper_site_url": "https://wallpapercave.com",

    "wallpaper_url": "https://wallpapercave.com/wp/wp4678292.jpg"

  },
   {

    "wallpaper_index": "4360",

    "wallpaper_name": "Frozen 2 HD-4k",

    "wallpaper_site_name": "imgur",

    "wallpaper_site_url": "https://wallpapercave.com",

    "wallpaper_url": "https://wallpapercave.com/wp/wp4531917.jpg"

  },
   {

    "wallpaper_index": "4370",

    "wallpaper_name": "Frozen 2 HD-4k",

    "wallpaper_site_name": "imgur",

    "wallpaper_site_url": "https://wallpapercave.com",

    "wallpaper_url": "https://wallpapercave.com/wp/wp4599591.png"

  },
   {

    "wallpaper_index": "4308",

    "wallpaper_name": "Frozen 2 HD-4k",

    "wallpaper_site_name": "imgur",

    "wallpaper_site_url": "https://wallpapercave.com",

    "wallpaper_url": "https://wallpaperaccess.com/full/229554.png"

  },
   {

    "wallpaper_index": "4390",

    "wallpaper_name": "Frozen 2 HD-4k",

    "wallpaper_site_name": "imgur",

    "wallpaper_site_url": "https://wallpapercave.com",

    "wallpaper_url": "https://wallpaperaccess.com/full/768923.png"

  },
   {

    "wallpaper_index": "4400",

    "wallpaper_name": "Frozen 2 HD-4k",

    "wallpaper_site_name": "imgur",

    "wallpaper_site_url": "https://wallpapercave.com",

    "wallpaper_url": "https://wallpaperaccess.com/full/768926.png"

  },
   {

    "wallpaper_index": "4410",

    "wallpaper_name": "Frozen 2 HD-4k",

    "wallpaper_site_name": "imgur",

    "wallpaper_site_url": "https://wallpapercave.com",

    "wallpaper_url": "https://wallpaperaccess.com/full/768928.png"

  },
   {

    "wallpaper_index": "4420",

    "wallpaper_name": "Frozen 2 HD-4k",

    "wallpaper_site_name": "imgur",

    "wallpaper_site_url": "https://wallpapercave.com",

    "wallpaper_url": "https://wallpaperaccess.com/full/768927.png"

  },
   {

    "wallpaper_index": "4430",

    "wallpaper_name": "Frozen 2 HD-4k",

    "wallpaper_site_name": "imgur",

    "wallpaper_site_url": "https://wallpapercave.com",

    "wallpaper_url": "https://wallpaperaccess.com/full/768931.png"

  },
   {

    "wallpaper_index": "4440",

    "wallpaper_name": "Frozen 2 HD-4k",

    "wallpaper_site_name": "imgur",

    "wallpaper_site_url": "https://wallpapercave.com",

    "wallpaper_url": "https://wallpaperaccess.com/full/768937.png"

  },
   {

    "wallpaper_index": "4405",

    "wallpaper_name": "Frozen 2 HD-4k",

    "wallpaper_site_name": "imgur",

    "wallpaper_site_url": "https://wallpapercave.com",

    "wallpaper_url": "https://wallpaperaccess.com/full/768942.png"

  },
   {

    "wallpaper_index": "4460",

    "wallpaper_name": "Frozen 2 HD-4k",

    "wallpaper_site_name": "imgur",

    "wallpaper_site_url": "https://wallpapercave.com",

    "wallpaper_url": "https://wallpaperaccess.com/full/768943.png"

  },
   {

    "wallpaper_index": "4470",

    "wallpaper_name": "Frozen 2 HD-4k",

    "wallpaper_site_name": "imgur",

    "wallpaper_site_url": "https://wallpapercave.com",

    "wallpaper_url": "https://wallpaperaccess.com/full/768953.png"

  },
   {

    "wallpaper_index": "4480",

    "wallpaper_name": "Frozen 2 HD-4k",

    "wallpaper_site_name": "imgur",

    "wallpaper_site_url": "https://wallpapercave.com",

    "wallpaper_url": "https://wallpaperaccess.com/full/768959.png"

  },
   {

    "wallpaper_index": "45000",

    "wallpaper_name": "Frozen 2 HD-4k",

    "wallpaper_site_name": "imgur",

    "wallpaper_site_url": "https://wallpapercave.com",

    "wallpaper_url": "https://wallpapercave.com/wp/wp4599548.jpg"

  },
   {

    "wallpaper_index": "4490",

    "wallpaper_name": "Frozen 2 HD-4k",

    "wallpaper_site_name": "imgur",

    "wallpaper_site_url": "https://wallpapercave.com",

    "wallpaper_url": "https://wallpapercave.com/wp/wp1984781.jpg"

  },
   {

    "wallpaper_index": "4510",

    "wallpaper_name": "Frozen 2 HD-4k",

    "wallpaper_site_name": "imgur",

    "wallpaper_site_url": "https://wallpapercave.com",

    "wallpaper_url": "https://wallpapercave.com/wp/wp4599594.jpg"

  },
   {

    "wallpaper_index": "4520",

    "wallpaper_name": "Frozen 2 HD-4k",

    "wallpaper_site_name": "imgur",

    "wallpaper_site_url": "https://wallpapercave.com",

    "wallpaper_url": "https://wallpapercave.com/wp/wp4599605.png"

  },
   {

    "wallpaper_index": "4530",
    
    "wallpaper_name": "Frozen 2 HD-4k",

    "wallpaper_site_name": "imgur",

    "wallpaper_site_url": "https://wallpapercave.com",

    "wallpaper_url": "https://wallpapercave.com/wp/wp4599606.jpg"

  },
   {

    "wallpaper_index": "4540",

    "wallpaper_name": "Frozen 2 HD-4k",

    "wallpaper_site_name": "imgur",

    "wallpaper_site_url": "https://wallpapercave.com",

    "wallpaper_url": "https://wallpapercave.com/wp/wp4599611.jpg"

  },
   {

    "wallpaper_index": "4560",

    "wallpaper_name": "Frozen 2 HD-4k",

    "wallpaper_site_name": "imgur",

    "wallpaper_site_url": "https://wallpapercave.com",

    "wallpaper_url": "https://wallpapercave.com/wp/wp4599613.jpg"

  },
   {

    "wallpaper_index": "4570",

    "wallpaper_name": "Frozen 2 HD-4k",

    "wallpaper_site_name": "imgur",

    "wallpaper_site_url": "https://wallpapercave.com",

    "wallpaper_url": "https://wallpapercave.com/wp/wp3716196.jpg"

  },
   {

    "wallpaper_index": "4580",

    "wallpaper_name": "Frozen 2 HD-4k",

    "wallpaper_site_name": "imgur",

    "wallpaper_site_url": "https://wallpapercave.com",

    "wallpaper_url": "https://wallpapercave.com/wp/wp4599618.jpg"

  },
     {

    "wallpaper_index": "4050",

    "wallpaper_name": "Frozen 2 HD-4k",

    "wallpaper_site_name": "imgur",

    "wallpaper_site_url": "https://wallpapercave.com",

    "wallpaper_url": "https://wallpapercave.com/wp/wp4413314.jpg"

  },
    {

    "wallpaper_index": "4060",

    "wallpaper_name": "Frozen 2 HD-4k",

    "wallpaper_site_name": "imgur",

    "wallpaper_site_url": "https://wallpapercave.com",

    "wallpaper_url": "https://wallpapercave.com/wp/wp4678240.jpg"

  },
    {

    "wallpaper_index": "40070",

    "wallpaper_name": "Frozen 2 HD-4k",

    "wallpaper_site_name": "imgur",

    "wallpaper_site_url": "https://wallpapercave.com",

    "wallpaper_url": "https://wallpapercave.com/wp/wp4678241.jpg"

  },
    {

    "wallpaper_index": "4080",

    "wallpaper_name": "Frozen 2 HD-4k",

    "wallpaper_site_name": "imgur",

    "wallpaper_site_url": "https://wallpapercave.com",

    "wallpaper_url": "https://wallpapercave.com/wp/wp4678242.jpg"

  },
    {

    "wallpaper_index": "4090",

    "wallpaper_name": "Frozen 2 HD-4k",

    "wallpaper_site_name": "imgur",

    "wallpaper_site_url": "https://wallpapercave.com",

    "wallpaper_url": "https://wallpapercave.com/wp/wp4599551.jpg"

  },
    {

    "wallpaper_index": "4100",

    "wallpaper_name": "Frozen 2 HD-4k",

    "wallpaper_site_name": "imgur",

    "wallpaper_site_url": "https://wallpapercave.com",

    "wallpaper_url": "https://wallpapercave.com/wp/wp4531891.jpg"

  },
    {

    "wallpaper_index": "4101",

    "wallpaper_name": "Frozen 2 HD-4k",

    "wallpaper_site_name": "imgur",

    "wallpaper_site_url": "https://wallpapercave.com",

    "wallpaper_url": "https://wallpapercave.com/wp/wp4678245.jpg"

  },
    {

    "wallpaper_index": "4012",

    "wallpaper_name": "Frozen 2 HD-4k",

    "wallpaper_site_name": "imgur",

    "wallpaper_site_url": "https://wallpapercave.com",

    "wallpaper_url": "https://wallpapercave.com/wp/wp1987829.jpg"

  },
    {

    "wallpaper_index": "413",

    "wallpaper_name": "Frozen 2 HD-4k",

    "wallpaper_site_name": "imgur",

    "wallpaper_site_url": "https://wallpapercave.com",

    "wallpaper_url": "https://wallpapercave.com/wp/wp4531894.jpg"

  },
    {

    "wallpaper_index": "414",

    "wallpaper_name": "Frozen 2 HD-4k",

    "wallpaper_site_name": "imgur",

    "wallpaper_site_url": "https://wallpapercave.com",

    "wallpaper_url": "https://wallpapercave.com/w/wp1984701"

  },
    {

    "wallpaper_index": "415",

    "wallpaper_name": "Frozen 2 HD-4k",

    "wallpaper_site_name": "imgur",

    "wallpaper_site_url": "https://wallpapercave.com",

    "wallpaper_url": "https://wallpapercave.com/wp/wp4599576.jpg"

  },
    {

    "wallpaper_index": "416",

    "wallpaper_name": "Frozen 2 HD-4k",

    "wallpaper_site_name": "imgur",

    "wallpaper_site_url": "https://wallpapercave.com",

    "wallpaper_url": "https://wallpapercave.com/wp/wp4678250.jpg"

  },
    {

    "wallpaper_index": "417",

    "wallpaper_name": "Frozen 2 HD-4k",

    "wallpaper_site_name": "imgur",

    "wallpaper_site_url": "https://wallpapercave.com",

    "wallpaper_url": "https://wallpapercave.com/wp/wp4531898.jpg"

  },
    {

    "wallpaper_index": "418",

    "wallpaper_name": "Frozen 2 HD-4k",

    "wallpaper_site_name": "imgur",

    "wallpaper_site_url": "https://wallpapercave.com",

    "wallpaper_url": "https://wallpapercave.com/wp/wp1987896.jpg"

  },
    {

    "wallpaper_index": "419",

    "wallpaper_name": "Frozen 2 HD-4k",

    "wallpaper_site_name": "imgur",

    "wallpaper_site_url": "https://wallpapercave.com",

    "wallpaper_url": "https://wallpapercave.com/wp/wp4678253.jpg"

  },
    {

    "wallpaper_index": "420",

    "wallpaper_name": "Frozen 2 HD-4k",

    "wallpaper_site_name": "imgur",

    "wallpaper_site_url": "https://wallpapercave.com",

    "wallpaper_url": "https://wallpapercave.com/wp/wp4599613.jpg"

  },
    {

    "wallpaper_index": "421",

    "wallpaper_name": "Frozen 2 HD-4k",

    "wallpaper_site_name": "imgur",

    "wallpaper_site_url": "https://wallpapercave.com",

    "wallpaper_url": "https://wallpapercave.com/wp/wp4678257.jpg"

  },
    {

    "wallpaper_index": "422",

    "wallpaper_name": "Frozen 2 HD-4k",

    "wallpaper_site_name": "imgur",

    "wallpaper_site_url": "https://wallpapercave.com",

    "wallpaper_url": "https://wallpapercave.com/wp/wp4678261.jpg"

  },
    {

    "wallpaper_index": "423",

    "wallpaper_name": "Frozen 2 HD-4k",

    "wallpaper_site_name": "imgur",

    "wallpaper_site_url": "https://wallpapercave.com",

    "wallpaper_url": "https://wallpapercave.com/wp/wp4678269.jpg"

  },
    {

    "wallpaper_index": "424",

    "wallpaper_name": "Frozen 2 HD-4k",

    "wallpaper_site_name": "imgur",

    "wallpaper_site_url": "https://wallpapercave.com",

    "wallpaper_url": "https://wallpapercave.com/wp/wp4599574.png"

  },
    {

    "wallpaper_index": "425",

    "wallpaper_name": "Frozen 2 HD-4k",

    "wallpaper_site_name": "imgur",

    "wallpaper_site_url": "https://wallpapercave.com",

    "wallpaper_url": "https://wallpapercave.com/wp/wp4678271.jpg"

  },
    {

    "wallpaper_index": "426",

    "wallpaper_name": "Frozen 2 HD-4k",

    "wallpaper_site_name": "imgur",

    "wallpaper_site_url": "https://wallpapercave.com",

    "wallpaper_url": "https://wallpapercave.com/wp/wp4531907.jpg"

  },
    {

    "wallpaper_index": "427",

    "wallpaper_name": "Frozen 2 HD-4k",

    "wallpaper_site_name": "imgur",

    "wallpaper_site_url": "https://wallpapercave.com",

    "wallpaper_url": "https://wallpapercave.com/wp/wp4413374.jpg"

  },
   {

    "wallpaper_index": "428",

    "wallpaper_name": "Frozen 2 HD-4k",

    "wallpaper_site_name": "imgur",

    "wallpaper_site_url": "https://wallpapercave.com",

    "wallpaper_url": "https://wallpapercave.com/wp/wp4678277.jpg"

  },
   {

    "wallpaper_index": "429",

    "wallpaper_name": "Frozen 2 HD-4k",

    "wallpaper_site_name": "imgur",

    "wallpaper_site_url": "https://wallpapercave.com",

    "wallpaper_url": "https://wallpapercave.com/wp/wp4531910.jpg"

  },
   {

    "wallpaper_index": "430",

    "wallpaper_name": "Frozen 2 HD-4k",

    "wallpaper_site_name": "imgur",

    "wallpaper_site_url": "https://wallpapercave.com",

    "wallpaper_url": "https://wallpapercave.com/wp/wp4678280.jpg"

  },
   {

    "wallpaper_index": "431",

    "wallpaper_name": "Frozen 2 HD-4k",

    "wallpaper_site_name": "imgur",

    "wallpaper_site_url": "https://wallpapercave.com",

    "wallpaper_url": "https://wallpapercave.com/wp/wp4678283.jpg"

  },
   {

    "wallpaper_index": "432",

    "wallpaper_name": "Frozen 2 HD-4k",

    "wallpaper_site_name": "imgur",

    "wallpaper_site_url": "https://wallpapercave.com",

    "wallpaper_url": "https://wallpapercave.com/wp/wp4531913.jpg"

  },
   {

    "wallpaper_index": "433",

    "wallpaper_name": "Frozen 2 HD-4k",

    "wallpaper_site_name": "imgur",

    "wallpaper_site_url": "https://wallpapercave.com",

    "wallpaper_url": "https://wallpapercave.com/wp/wp4678286.jpg"

  },
   {

    "wallpaper_index": "434",

    "wallpaper_name": "Frozen 2 HD-4k",

    "wallpaper_site_name": "imgur",

    "wallpaper_site_url": "https://wallpapercave.com",

    "wallpaper_url": "https://wallpapercave.com/wp/wp4678293.jpg"

  },
   {

    "wallpaper_index": "435",

    "wallpaper_name": "Frozen 2 HD-4k",

    "wallpaper_site_name": "imgur",

    "wallpaper_site_url": "https://wallpapercave.com",

    "wallpaper_url": "https://wallpapercave.com/wp/wp4678292.jpg"

  },
   {

    "wallpaper_index": "436",

    "wallpaper_name": "Frozen 2 HD-4k",

    "wallpaper_site_name": "imgur",

    "wallpaper_site_url": "https://wallpapercave.com",

    "wallpaper_url": "https://wallpapercave.com/wp/wp4531917.jpg"

  },
   {

    "wallpaper_index": "437",

    "wallpaper_name": "Frozen 2 HD-4k",

    "wallpaper_site_name": "imgur",

    "wallpaper_site_url": "https://wallpapercave.com",

    "wallpaper_url": "https://wallpapercave.com/wp/wp4599591.png"

  },
   {

    "wallpaper_index": "438",

    "wallpaper_name": "Frozen 2 HD-4k",

    "wallpaper_site_name": "imgur",

    "wallpaper_site_url": "https://wallpapercave.com",

    "wallpaper_url": "https://wallpaperaccess.com/full/229554.png"

  },
   {

    "wallpaper_index": "439",

    "wallpaper_name": "Frozen 2 HD-4k",

    "wallpaper_site_name": "imgur",

    "wallpaper_site_url": "https://wallpapercave.com",

    "wallpaper_url": "https://wallpaperaccess.com/full/768923.png"

  },
   {

    "wallpaper_index": "440",

    "wallpaper_name": "Frozen 2 HD-4k",

    "wallpaper_site_name": "imgur",

    "wallpaper_site_url": "https://wallpapercave.com",

    "wallpaper_url": "https://wallpaperaccess.com/full/768926.png"

  },
   {

    "wallpaper_index": "441",

    "wallpaper_name": "Frozen 2 HD-4k",

    "wallpaper_site_name": "imgur",

    "wallpaper_site_url": "https://wallpapercave.com",

    "wallpaper_url": "https://wallpaperaccess.com/full/768928.png"

  },
   {

    "wallpaper_index": "442",

    "wallpaper_name": "Frozen 2 HD-4k",

    "wallpaper_site_name": "imgur",

    "wallpaper_site_url": "https://wallpapercave.com",

    "wallpaper_url": "https://wallpaperaccess.com/full/768927.png"

  },
   {

    "wallpaper_index": "443",

    "wallpaper_name": "Frozen 2 HD-4k",

    "wallpaper_site_name": "imgur",

    "wallpaper_site_url": "https://wallpapercave.com",

    "wallpaper_url": "https://wallpaperaccess.com/full/768931.png"

  },
   {

    "wallpaper_index": "444",

    "wallpaper_name": "Frozen 2 HD-4k",

    "wallpaper_site_name": "imgur",

    "wallpaper_site_url": "https://wallpapercave.com",

    "wallpaper_url": "https://wallpaperaccess.com/full/768937.png"

  },
   {

    "wallpaper_index": "445",

    "wallpaper_name": "Frozen 2 HD-4k",

    "wallpaper_site_name": "imgur",

    "wallpaper_site_url": "https://wallpapercave.com",

    "wallpaper_url": "https://wallpaperaccess.com/full/768942.png"

  },
   {

    "wallpaper_index": "446",

    "wallpaper_name": "Frozen 2 HD-4k",

    "wallpaper_site_name": "imgur",

    "wallpaper_site_url": "https://wallpapercave.com",

    "wallpaper_url": "https://wallpaperaccess.com/full/768943.png"

  },
   {

    "wallpaper_index": "447",

    "wallpaper_name": "Frozen 2 HD-4k",

    "wallpaper_site_name": "imgur",

    "wallpaper_site_url": "https://wallpapercave.com",

    "wallpaper_url": "https://wallpaperaccess.com/full/768953.png"

  },
   {

    "wallpaper_index": "448",

    "wallpaper_name": "Frozen 2 HD-4k",

    "wallpaper_site_name": "imgur",

    "wallpaper_site_url": "https://wallpapercave.com",

    "wallpaper_url": "https://wallpaperaccess.com/full/768959.png"

  },
   {

    "wallpaper_index": "450",

    "wallpaper_name": "Frozen 2 HD-4k",

    "wallpaper_site_name": "imgur",

    "wallpaper_site_url": "https://wallpapercave.com",

    "wallpaper_url": "https://wallpapercave.com/wp/wp4599548.jpg"

  },
   {

    "wallpaper_index": "449",

    "wallpaper_name": "Frozen 2 HD-4k",

    "wallpaper_site_name": "imgur",

    "wallpaper_site_url": "https://wallpapercave.com",

    "wallpaper_url": "https://wallpapercave.com/wp/wp1984781.jpg"

  },
   {

    "wallpaper_index": "451",

    "wallpaper_name": "Frozen 2 HD-4k",

    "wallpaper_site_name": "imgur",

    "wallpaper_site_url": "https://wallpapercave.com",

    "wallpaper_url": "https://wallpapercave.com/wp/wp4599594.jpg"

  },
   {

    "wallpaper_index": "452",

    "wallpaper_name": "Frozen 2 HD-4k",

    "wallpaper_site_name": "imgur",

    "wallpaper_site_url": "https://wallpapercave.com",

    "wallpaper_url": "https://wallpapercave.com/wp/wp4599605.png"

  },
   {

    "wallpaper_index": "453",
    
    "wallpaper_name": "Frozen 2 HD-4k",

    "wallpaper_site_name": "imgur",

    "wallpaper_site_url": "https://wallpapercave.com",

    "wallpaper_url": "https://wallpapercave.com/wp/wp4599606.jpg"

  },
   {

    "wallpaper_index": "454",

    "wallpaper_name": "Frozen 2 HD-4k",

    "wallpaper_site_name": "imgur",

    "wallpaper_site_url": "https://wallpapercave.com",

    "wallpaper_url": "https://wallpapercave.com/wp/wp4599611.jpg"

  },
   {

    "wallpaper_index": "456",

    "wallpaper_name": "Frozen 2 HD-4k",

    "wallpaper_site_name": "imgur",

    "wallpaper_site_url": "https://wallpapercave.com",

    "wallpaper_url": "https://wallpapercave.com/wp/wp4599613.jpg"

  },
   {

    "wallpaper_index": "457",

    "wallpaper_name": "Frozen 2 HD-4k",

    "wallpaper_site_name": "imgur",

    "wallpaper_site_url": "https://wallpapercave.com",

    "wallpaper_url": "https://wallpapercave.com/wp/wp3716196.jpg"

  },
   {

    "wallpaper_index": "458",

    "wallpaper_name": "Frozen 2 HD-4k",

    "wallpaper_site_name": "imgur",

    "wallpaper_site_url": "https://wallpapercave.com",

    "wallpaper_url": "https://wallpapercave.com/wp/wp4599618.jpg"

  }
  
]


